elan/__init__.py
elan/ddeneme.py
elan/image_utils.py
elan/list_utils.py
elan/main.py
elan/math_utils.py
elan/string_utils.py
elan/video_utils.py
elan-0.3.9.dist-info/licenses/LICENSE
elan-0.3.9.dist-info/METADATA
elan-0.3.9.dist-info/WHEEL
elan-0.3.9.dist-info/top_level.txt
elan-0.3.9.dist-info/RECORD
